Metadata-Version: 2.1
Name: azure-cli-vm
Version: 2.2.23
Summary: Microsoft Azure Command-Line Tools VM Command Module
Home-page: https://github.com/Azure/azure-cli
Author: Microsoft Corporation
Author-email: azpycli@microsoft.com
License: MIT
Platform: UNKNOWN
Classifier: Development Status :: 5 - Production/Stable
Classifier: Intended Audience :: Developers
Classifier: Intended Audience :: System Administrators
Classifier: Programming Language :: Python
Classifier: Programming Language :: Python :: 2
Classifier: Programming Language :: Python :: 2.7
Classifier: Programming Language :: Python :: 3
Classifier: Programming Language :: Python :: 3.4
Classifier: Programming Language :: Python :: 3.5
Classifier: Programming Language :: Python :: 3.6
Classifier: License :: OSI Approved :: MIT License
Requires-Dist: azure-mgmt-msi (==0.2.0)
Requires-Dist: azure-mgmt-authorization (==0.50.0)
Requires-Dist: azure-mgmt-compute (==5.0.0)
Requires-Dist: azure-mgmt-keyvault (==1.1.0)
Requires-Dist: azure-keyvault (==1.1.0)
Requires-Dist: azure-mgmt-network (==3.0.0)
Requires-Dist: azure-multiapi-storage (==0.2.3)
Requires-Dist: azure-mgmt-marketplaceordering (==0.1.0)
Requires-Dist: azure-mgmt-imagebuilder (==0.2.1)
Requires-Dist: azure-cli-core
Requires-Dist: azure-cli-command-modules-nspkg (>=2.0.0)
